[
  { "pkdxNum": 1, "name": "Bulbasaur" },
  { "pkdxNum": 2, "name": "Ivysaur" },
  { "pkdxNum": 3, "name": "Venusaur" },
  { "pkdxNum": 4, "name": "Charmander" },
  { "pkdxNum": 5, "name": "Charmeleon" },
  { "pkdxNum": 6, "name": "Charizard" },
  { "pkdxNum": 7, "name": "Squirtle" },
  { "pkdxNum": 8, "name": "Wartortle" },
  { "pkdxNum": 9, "name": "Blastoise" },
  { "pkdxNum": 10, "name": "Caterpie" },
  { "pkdxNum": 11, "name": "Metapod" },
  { "pkdxNum": 12, "name": "Butterfree" },
  { "pkdxNum": 13, "name": "Weedle" },
  { "pkdxNum": 14, "name": "Kakuna" },
  { "pkdxNum": 15, "name": "Beedrill" },
  { "pkdxNum": 16, "name": "Pidgey" },
  { "pkdxNum": 17, "name": "Pidgeotto" },
  { "pkdxNum": 18, "name": "Pidgeot" },
  { "pkdxNum": 19, "name": "Rattata" },
  { "pkdxNum": 20, "name": "Raticate" },
  { "pkdxNum": 21, "name": "Spearow" },
  { "pkdxNum": 22, "name": "Fearow" },
  { "pkdxNum": 23, "name": "Ekans" },
  { "pkdxNum": 24, "name": "Arbok" },
  { "pkdxNum": 25, "name": "Pikachu" },
  { "pkdxNum": 26, "name": "Raichu" },
  { "pkdxNum": 27, "name": "Sandshrew" },
  { "pkdxNum": 28, "name": "Sandslash" },
  { "pkdxNum": 29, "name": "Nidoran♀" },
  { "pkdxNum": 30, "name": "Nidorina" },
  { "pkdxNum": 31, "name": "Nidoqueen" },
  { "pkdxNum": 32, "name": "Nidoran♂" },
  { "pkdxNum": 33, "name": "Nidorino" },
  { "pkdxNum": 34, "name": "Nidoking" },
  { "pkdxNum": 35, "name": "Clefairy" },
  { "pkdxNum": 36, "name": "Clefable" },
  { "pkdxNum": 37, "name": "Vulpix" },
  { "pkdxNum": 38, "name": "Ninetales" },
  { "pkdxNum": 39, "name": "Jigglypuff" },
  { "pkdxNum": 40, "name": "Wigglytuff" },
  { "pkdxNum": 41, "name": "Zubat" },
  { "pkdxNum": 42, "name": "Golbat" },
  { "pkdxNum": 43, "name": "Oddish" },
  { "pkdxNum": 44, "name": "Gloom" },
  { "pkdxNum": 45, "name": "Vileplume" },
  { "pkdxNum": 46, "name": "Paras" },
  { "pkdxNum": 47, "name": "Parasect" },
  { "pkdxNum": 48, "name": "Venonat" },
  { "pkdxNum": 49, "name": "Venomoth" },
  { "pkdxNum": 50, "name": "Diglett" },
  { "pkdxNum": 51, "name": "Dugtrio" },
  { "pkdxNum": 52, "name": "Meowth" },
  { "pkdxNum": 53, "name": "Persian" },
  { "pkdxNum": 54, "name": "Psyduck" },
  { "pkdxNum": 55, "name": "Golduck" },
  { "pkdxNum": 56, "name": "Mankey" },
  { "pkdxNum": 57, "name": "Primeape" },
  { "pkdxNum": 58, "name": "Growlithe" },
  { "pkdxNum": 59, "name": "Arcanine" },
  { "pkdxNum": 60, "name": "Poliwag" },
  { "pkdxNum": 61, "name": "Poliwhirl" },
  { "pkdxNum": 62, "name": "Poliwrath" },
  { "pkdxNum": 63, "name": "Abra" },
  { "pkdxNum": 64, "name": "Kadabra" },
  { "pkdxNum": 65, "name": "Alakazam" },
  { "pkdxNum": 66, "name": "Machop" },
  { "pkdxNum": 67, "name": "Machoke" },
  { "pkdxNum": 68, "name": "Machamp" },
  { "pkdxNum": 69, "name": "Bellsprout" },
  { "pkdxNum": 70, "name": "Weepinbell" },
  { "pkdxNum": 71, "name": "Victreebel" },
  { "pkdxNum": 72, "name": "Tentacool" },
  { "pkdxNum": 73, "name": "Tentacruel" },
  { "pkdxNum": 74, "name": "Geodude" },
  { "pkdxNum": 75, "name": "Graveler" },
  { "pkdxNum": 76, "name": "Golem" },
  { "pkdxNum": 77, "name": "Ponyta" },
  { "pkdxNum": 78, "name": "Rapidash" },
  { "pkdxNum": 79, "name": "Slowpoke" },
  { "pkdxNum": 80, "name": "Slowbro" },
  { "pkdxNum": 81, "name": "Magnemite" },
  { "pkdxNum": 82, "name": "Magneton" },
  { "pkdxNum": 83, "name": "Farfetch’d" },
  { "pkdxNum": 84, "name": "Doduo" },
  { "pkdxNum": 85, "name": "Dodrio" },
  { "pkdxNum": 86, "name": "Seel" },
  { "pkdxNum": 87, "name": "Dewgong" },
  { "pkdxNum": 88, "name": "Grimer" },
  { "pkdxNum": 89, "name": "Muk" },
  { "pkdxNum": 90, "name": "Shellder" },
  { "pkdxNum": 91, "name": "Cloyster" },
  { "pkdxNum": 92, "name": "Gastly" },
  { "pkdxNum": 93, "name": "Haunter" },
  { "pkdxNum": 94, "name": "Gengar" },
  { "pkdxNum": 95, "name": "Onix" },
  { "pkdxNum": 96, "name": "Drowzee" },
  { "pkdxNum": 97, "name": "Hypno" },
  { "pkdxNum": 98, "name": "Krabby" },
  { "pkdxNum": 99, "name": "Kingler" },
  { "pkdxNum": 100, "name": "Voltorb" },
  { "pkdxNum": 101, "name": "Electrode" },
  { "pkdxNum": 102, "name": "Exeggcute" },
  { "pkdxNum": 103, "name": "Exeggutor" },
  { "pkdxNum": 104, "name": "Cubone" },
  { "pkdxNum": 105, "name": "Marowak" },
  { "pkdxNum": 106, "name": "Hitmonlee" },
  { "pkdxNum": 107, "name": "Hitmonchan" },
  { "pkdxNum": 108, "name": "Lickitung" },
  { "pkdxNum": 109, "name": "Koffing" },
  { "pkdxNum": 110, "name": "Weezing" },
  { "pkdxNum": 111, "name": "Rhyhorn" },
  { "pkdxNum": 112, "name": "Rhydon" },
  { "pkdxNum": 113, "name": "Chansey" },
  { "pkdxNum": 114, "name": "Tangela" },
  { "pkdxNum": 115, "name": "Kangaskhan" },
  { "pkdxNum": 116, "name": "Horsea" },
  { "pkdxNum": 117, "name": "Seadra" },
  { "pkdxNum": 118, "name": "Goldeen" },
  { "pkdxNum": 119, "name": "Seaking" },
  { "pkdxNum": 120, "name": "Staryu" },
  { "pkdxNum": 121, "name": "Starmie" },
  { "pkdxNum": 122, "name": "Mr. Mime" },
  { "pkdxNum": 123, "name": "Scyther" },
  { "pkdxNum": 124, "name": "Jynx" },
  { "pkdxNum": 125, "name": "Electabuzz" },
  { "pkdxNum": 126, "name": "Magmar" },
  { "pkdxNum": 127, "name": "Pinsir" },
  { "pkdxNum": 128, "name": "Tauros" },
  { "pkdxNum": 129, "name": "Magikarp" },
  { "pkdxNum": 130, "name": "Gyarados" },
  { "pkdxNum": 131, "name": "Lapras" },
  { "pkdxNum": 132, "name": "Ditto" },
  { "pkdxNum": 133, "name": "Eevee" },
  { "pkdxNum": 134, "name": "Vaporeon" },
  { "pkdxNum": 135, "name": "Jolteon" },
  { "pkdxNum": 136, "name": "Flareon" },
  { "pkdxNum": 137, "name": "Porygon" },
  { "pkdxNum": 138, "name": "Omanyte" },
  { "pkdxNum": 139, "name": "Omastar" },
  { "pkdxNum": 140, "name": "Kabuto" },
  { "pkdxNum": 141, "name": "Kabutops" },
  { "pkdxNum": 142, "name": "Aerodactyl" },
  { "pkdxNum": 143, "name": "Snorlax" },
  { "pkdxNum": 144, "name": "Articuno" },
  { "pkdxNum": 145, "name": "Zapdos" },
  { "pkdxNum": 146, "name": "Moltres" },
  { "pkdxNum": 147, "name": "Dratini" },
  { "pkdxNum": 148, "name": "Dragonair" },
  { "pkdxNum": 149, "name": "Dragonite" },
  { "pkdxNum": 150, "name": "Mewtwo" },
  { "pkdxNum": 151, "name": "Mew" }
]
